pyairpar/__init__.py
pyairpar/core/__init__.py
pyairpar/core/airfoil.py
pyairpar/core/anchor_point.py
pyairpar/core/base_airfoil_params.py
pyairpar/core/free_point.py
pyairpar/core/param.py
pyairpar/core/param_setup.py
pyairpar/core/parametrization.py
pyairpar/examples/__init__.py
pyairpar/examples/airfoil_matching.py
pyairpar/examples/complex_airfoil.py
pyairpar/examples/high_lift.py
pyairpar/examples/mirrored_subsection.py
pyairpar/examples/propulsion_airframe_integration.py
pyairpar/examples/simple_airfoil.py
pyairpar/examples/symm_airfoil.py
pyairpar/symmetric/__init__.py
pyairpar/symmetric/symmetric_airfoil.py
pyairpar/symmetric/symmetric_base_airfoil_params.py
pyairpar/utils/__init__.py
pyairpar/utils/airfoil_matching.py
pyairpar/utils/get_airfoil.py
pyairpar/utils/transformations.py
pyairpar-1.1.1.dist-info/METADATA
pyairpar-1.1.1.dist-info/WHEEL
pyairpar-1.1.1.dist-info/top_level.txt
pyairpar-1.1.1.dist-info/RECORD
