Metadata-Version: 2.1
Name: pyairpar
Version: 1.1.1
Summary: Generate Bézier-parametrized airfoils and airfoil systems
Home-page: https://github.com/mlau154/pyairpar
Author: Matthew G Lauer
Author-email: mlauer2015@gmail.com
License: MIT
Platform: UNKNOWN
Classifier: License :: OSI Approved :: MIT License
Classifier: Programming Language :: Python :: 3
Requires-Dist: scipy
Requires-Dist: numpy
Requires-Dist: shapely
Requires-Dist: matplotlib
Requires-Dist: requests
